{
  "@context": "https://w3id.org/codemeta/3.0",
  "type": "SoftwareSourceCode",
  "applicationCategory": "research data management",
  "author": [
    {
      "id": "https://orcid.org/0000-0001-6285-3242",
      "type": "Person",
      "affiliation": {
        "type": "Organization",
        "name": "DLR e.V."
      },
      "email": "Tobias.Haase@dlr.de",
      "familyName": "Haase",
      "givenName": "Tobias"
    },
    {
      "id": "https://orcid.org/0000-0001-7909-1942",
      "type": "Person",
      "affiliation": {
        "type": "Organization",
        "name": "DLR e.V."
      },
      "email": "Roland.Glueck@dlr.de",
      "familyName": "Glück",
      "givenName": "Roland"
    },
    {
      "id": "https://orcid.org/0000-0003-1181-7211",
      "type": "Person",
      "affiliation": {
        "type": "Organization",
        "name": "DLR e.V."
      },
      "email": "Patrick.Kaufmann@dlr.de",
      "familyName": "Kaufmann",
      "givenName": "Patrick"
    },
    {
      "id": "https://orcid.org/0000-0001-6033-801X",
      "type": "Person",
      "affiliation": {
        "type": "Organization",
        "name": "DLR e.V."
      },
      "email": "Florian.Krebs@dlr.de",
      "familyName": "Krebs",
      "givenName": "Florian"
    },
    {
      "id": "_:author_5",
      "type": "Person",
      "email": "Mark.Willmeroth@premium-aerotec.com",
      "familyName": "Willmeroth",
      "givenName": "Mark"
    }
  ],
  "codeRepository": "https://gitlab.com/dlr-shepard/shepard",
  "description": "shepard is a multi-database storage system for highly heterogenous research data. It provides a consistent API to deposit or access any type of supported data.",
  "identifier": "10.5281/zenodo.5091603",
  "keywords": ["data management", "research data", "process data", "digital twin"],
  "license": "https://spdx.org/licenses/Apache-2.0",
  "name": "shepard",
  "programmingLanguage": ["Java", "Typescript"],
  "relatedLink": "https://www.dlr.de/zlp/en/desktopdefault.aspx/tabid-18285/29082_read-76551/#/gallery/37839",
  "version": "1.0.0",
  "developmentStatus": "active"
}
